[
  {
    "_id": "6320a3ed2766946e64c59fc9",
    "valid": true,
    "number": 19188517829,
    "local_format": 9188517829,
    "international_format": 19188517829,
    "country_prefix": 1,
    "country_code": "US",
    "country_name": "United States of America",
    "location": "Tulsa",
    "carrier": "T-Mobile USA Inc.",
    "line_type": "mobile",
    "__v": 0
  },
  {
    "_id": "6320a3ee2766946e64c59fcb",
    "valid": true,
    "number": 17653981909,
    "local_format": 7653981909,
    "international_format": 17653981909,
    "country_prefix": 1,
    "country_code": "US",
    "country_name": "United States of America",
    "location": "Kokomo",
    "carrier": "T-Mobile USA Inc.",
    "line_type": "mobile",
    "__v": 0
  }
]
